meeshkan_hosted_authenticate/__init__.py
meeshkan_hosted_authenticate-0.5.dist-info/LICENSE
meeshkan_hosted_authenticate-0.5.dist-info/METADATA
meeshkan_hosted_authenticate-0.5.dist-info/WHEEL
meeshkan_hosted_authenticate-0.5.dist-info/top_level.txt
meeshkan_hosted_authenticate-0.5.dist-info/RECORD
