Metadata-Version: 2.1
Name: meeshkan-hosted-authenticate
Version: 0.5
Summary: Utility package to to verify firebase access tokens on meeshkan.io
Home-page: https://github.com/meeshkan/meeshkan-hosted-authenticate
Author: Meeshkan Dev Team
Author-email: dev@meeshkan.com
License: MIT
Platform: UNKNOWN
Requires-Dist: firebase-admin
Requires-Dist: meeshkan-hosted-secrets (==0.5)
